localflavor/__init__.py
localflavor/administrative_areas.py
localflavor/base.py
localflavor/exceptions.py
localflavor/generate_administrative_areas.py
localflavor/stub.py
localflavor/ar/__init__.py
localflavor/ar/ar_provinces.py
localflavor/ar/forms.py
localflavor/at/__init__.py
localflavor/at/at_states.py
localflavor/at/forms.py
localflavor/au/__init__.py
localflavor/au/au_states.py
localflavor/au/forms.py
localflavor/be/__init__.py
localflavor/be/be_provinces.py
localflavor/be/be_regions.py
localflavor/be/forms.py
localflavor/br/__init__.py
localflavor/br/br_states.py
localflavor/br/forms.py
localflavor/ca/__init__.py
localflavor/ca/ca_provinces.py
localflavor/ca/forms.py
localflavor/ch/__init__.py
localflavor/ch/ch_cantons.py
localflavor/ch/forms.py
localflavor/cn/__init__.py
localflavor/cn/cn_provinces.py
localflavor/cn/forms.py
localflavor/cu/__init__.py
localflavor/cu/choices.py
localflavor/cu/forms.py
localflavor/cz/__init__.py
localflavor/cz/cz_regions.py
localflavor/cz/forms.py
localflavor/de/__init__.py
localflavor/de/de_states.py
localflavor/de/forms.py
localflavor/dk/__init__.py
localflavor/dk/dk_municipalities.py
localflavor/dk/dk_postalcodes.py
localflavor/dk/forms.py
localflavor/ee/__init__.py
localflavor/ee/ee_counties.py
localflavor/ee/forms.py
localflavor/es/__init__.py
localflavor/es/es_provinces.py
localflavor/es/es_regions.py
localflavor/es/forms.py
localflavor/fi/__init__.py
localflavor/fi/fi_municipalities.py
localflavor/fi/forms.py
localflavor/fr/__init__.py
localflavor/fr/forms.py
localflavor/fr/fr_department.py
localflavor/fr/fr_region.py
localflavor/gb/__init__.py
localflavor/gb/forms.py
localflavor/gb/gb_regions.py
localflavor/generic/__init__.py
localflavor/generic/checksums.py
localflavor/generic/forms.py
localflavor/generic/validators.py
localflavor/generic/countries/__init__.py
localflavor/generic/countries/calling_codes.py
localflavor/generic/countries/iso_3166.py
localflavor/generic/countries/sepa.py
localflavor-1.9.dist-info/LICENSE
localflavor-1.9.dist-info/METADATA
localflavor-1.9.dist-info/WHEEL
localflavor-1.9.dist-info/top_level.txt
localflavor-1.9.dist-info/RECORD
