Metadata-Version: 1.1
Name: localflavor
Version: 1.9
Summary: Country-specific validation helpers, ported from Django Localflavor
Home-page: https://github.com/anka-sirota/localflavor
Author: Anna Sirota
Author-email: dev.local@gmail.com
License: BSD
Platform: UNKNOWN
Classifier: Development Status :: 5 - Production/Stable
Classifier: Environment :: Web Environment
Classifier: Intended Audience :: Developers
Classifier: License :: OSI Approved :: BSD License
Classifier: Operating System :: OS Independent
Classifier: Programming Language :: Python :: 3.6
Classifier: Topic :: Internet :: WWW/HTTP
